ko_ww_stopwords/__init__.py
ko_ww_stopwords/stop_words.py
ko_ww_stopwords/tools.py
ko_ww_stopwords-0.0.1.dist-info/METADATA
ko_ww_stopwords-0.0.1.dist-info/WHEEL
ko_ww_stopwords-0.0.1.dist-info/top_level.txt
ko_ww_stopwords-0.0.1.dist-info/RECORD
