Metadata-Version: 2.1
Name: ko-ww-stopwords
Version: 0.0.1
Summary: Set of whole-word (independent) stop words in Korean.
Home-page: https://github.com/Rairye/ko-ww-stopwords
Author: Rairye
License: apache-2.0
Download-URL: https://github.com/Rairye/ko-ww-stopwords/archive/refs/tags/v0.0.1.tar.gz
Keywords: Korean,stops,stop,words
Platform: UNKNOWN
Classifier: Development Status :: 3 - Alpha
Classifier: Intended Audience :: End Users/Desktop
Classifier: Intended Audience :: Developers
Classifier: License :: OSI Approved :: Apache Software License
Classifier: Programming Language :: Python :: 3
Classifier: Programming Language :: Python :: 3.1
Classifier: Programming Language :: Python :: 3.2
Classifier: Programming Language :: Python :: 3.3
Classifier: Programming Language :: Python :: 3.4
Classifier: Programming Language :: Python :: 3.5
Classifier: Programming Language :: Python :: 3.6
Classifier: Programming Language :: Python :: 3.7
